{
  "marketId": 550,
  "creator": "dE2cVL9QAgh3MZEK3ZhPG5S2YSqZET8V1Qa36epaU4pQG4pd8",
  "creation": "Permissionless",
  "creatorFee": 0,
  "oracle": "dE2cVL9QAgh3MZEK3ZhPG5S2YSqZET8V1Qa36epaU4pQG4pd8",
  "period": {
    "block": [
      2826024,
      2826092
    ]
  },
  "scoringRule": "CPMM",
  "marketType": {
    "categorical": 2
  },
  "status": "Resolved",
  "report": {
    "at": 2826325,
    "by": "dE2cVL9QAgh3MZEK3ZhPG5S2YSqZET8V1Qa36epaU4pQG4pd8",
    "outcome": {
      "categorical": 0
    }
  },
  "resolvedOutcome": "0",
  "disputeMechanism": "Authorized",
  "outcomeAssets": [
    {
      "categoricalOutcome": [
        550,
        0
      ]
    },
    {
      "categoricalOutcome": [
        550,
        1
      ]
    }
  ],
  "end": "1675317438022",
  "start": "1675316622022",
  "metadata": "0x1530b05e0fa43f72fd31dd959cd27b3b3171888eac57d233dfd39a2f282d51c61c6c3b695757995367cb4eea8d605530edf0",
  "deadlines": {
    "gracePeriod": "0",
    "oracleDuration": "7200",
    "disputeDuration": "28800"
  },
  "slug": "Testing portfolio 1",
  "question": "Will positions for loosing outcomes show after the winning outcome only was redeemed.",
  "description": "<p>Testing portfolio</p>",
  "categories": [
    {
      "ticker": "WO",
      "name": "Winning",
      "color": "#73ff00"
    },
    {
      "ticker": "LW",
      "name": "Loosing",
      "color": "#ff7200"
    }
  ],
  "tags": [
    "Technology"
  ],
  "scalarType": null,
  "poolId": 186
}
